{
  "_Table": "Technology",
  "ID": "MAINT_FRIG4",
  "Group": "",
  "Name": {
    "English": "SERVO ARM",
    "SimplifiedChinese": "伺服臂",
    "TencentChinese": "伺服臂",
    "TraditionalChinese": "伺服機械臂"
  },
  "NameLower": {
    "English": "Servo Arm",
    "SimplifiedChinese": "伺服臂",
    "TencentChinese": "伺服臂",
    "TraditionalChinese": "伺服機械臂"
  },
  "Subtitle": {
    "English": "Damaged Component",
    "SimplifiedChinese": "受损部件",
    "TencentChinese": "受损部件",
    "TraditionalChinese": "元件受損"
  },
  "Description": {
    "English": "A small mechanical joint, used to correct small mechanical errors across the device. A malfunction is causing it to take functional components and push them into the wrong place, creating even more damage.",
    "SimplifiedChinese": "小型机械接头，用于修正设备的微小机械错误。由于发生故障，使其部件功能失灵，并将其置于错误位置，造成更多损坏。",
    "TencentChinese": "小型机械接头，用于修正设备的微小机械错误。由于发生故障，使其部件功能失灵，并将其置于错误位置，造成更多损坏。",
    "TraditionalChinese": "小型機械接頭，用來修正裝置各處細微的機械錯誤。運轉失常導致接頭將正常部件推入錯誤位置，造成更多損害。"
  },
  "Teach": false,
  "HintStart": "",
  "HintEnd": "",
  "Icon": "ui-frontend-icons-update3-tradeprod.component4.png",
  "Colour": {
    "R": 0.0352941193,
    "G": 0.360784322,
    "B": 0.466666669,
    "A": 1
  },
  "Level": 1,
  "Chargeable": false,
  "ChargeAmount": 100,
  "ChargeType": "Earth",
  "ChargeBy": null,
  "ChargeMultiplier": 1,
  "BuildFullyCharged": true,
  "UsesAmmo": false,
  "AmmoId": "",
  "PrimaryItem": false,
  "Upgrade": false,
  "Core": true,
  "RepairTech": false,
  "Procedural": false,
  "BrokenSlotTech": false,
  "Category": "Maintenance",
  "Rarity": "Impossible",
  "Value": 10,
  "Requirements": {
    "LAND2": {
      "ID": "LAND2",
      "Type": "Substance",
      "Amount": 50
    }
  },
  "BaseStat": "Unspecified",
  "StatBonuses": null,
  "RequiredTech": "",
  "RequiredLevel": 0,
  "FocusLocator": "",
  "UpgradeColour": {
    "R": 1,
    "G": 1,
    "B": 1,
    "A": 1
  },
  "LinkColour": {
    "R": 1,
    "G": 1,
    "B": 1,
    "A": 1
  },
  "RewardGroup": "",
  "BaseValue": 1,
  "Cost": {
    "SpaceStationMarkup": 0,
    "LowPriceMod": 0,
    "HighPriceMod": 0,
    "BuyBaseMarkup": 0,
    "BuyMarkupMod": 0
  },
  "RequiredRank": 1,
  "DispensingRace": "None",
  "FragmentCost": 2,
  "TechShopRarity": "Impossible",
  "WikiEnabled": false,
  "NeverPinnable": false,
  "DamagedDescription": "",
  "ParentTechId": "",
  "IsTemplate": false,
  "ExclusivePrimaryStat": false
}