{
  "_Table": "Product",
  "ID": "FOOD_M_DIGGER",
  "Name": {
    "English": "DIRTY MEAT",
    "SimplifiedChinese": "肮脏的肉",
    "TraditionalChinese": "骯髒肉"
  },
  "NameLower": {
    "English": "Dirty Meat",
    "SimplifiedChinese": "肮脏的肉",
    "TraditionalChinese": "骯髒肉"
  },
  "Subtitle": {
    "English": "Raw Ingredient",
    "SimplifiedChinese": "原料",
    "TencentChinese": "原料",
    "TraditionalChinese": "原料"
  },
  "Description": {
    "English": "A nutritious meat product, harvested from the corpse of the creature that once contained it.<br><br>Process in a <span class=\"name name-technology\">Nutrient Processor</span> to generate edible products.",
    "SimplifiedChinese": "营养丰富的肉制品，从拥有它的动物尸体上收取。<br><br>使用<span class=\"name name-technology\">营养处理器</span>生成可食用产品。",
    "TencentChinese": "营养丰富的肉制品，从拥有它的动物尸体上收取。<br><br>使用<span class=\"name name-technology\">营养处理器</span>加工，即可生成可食用产品。",
    "TraditionalChinese": "營養豐富的肉製品，從擁有它的動物的屍體上收取。<br><br>用<span class=\"name name-technology\">營養處理器</span>加工即可生成可食用產品。"
  },
  "AltDescription": "",
  "Hint": "",
  "BuildableShipTechID": "",
  "GroupID": "",
  "[IGNORED]DebrisFile": null,
  "BaseValue": 1400,
  "Level": 0,
  "Icon": "ui-frontend-icons-cookingproducts-product.meat.raw.png",
  "HeroIcon": null,
  "Colour": {
    "R": 0.733333349,
    "G": 0.219607845,
    "B": 0.188235298,
    "A": 1
  },
  "Category": "Exotic",
  "Type": "Consumable",
  "Rarity": "Common",
  "Legality": "Legal",
  "Consumable": true,
  "ChargeValue": 0,
  "StackMultiplier": 10,
  "DefaultCraftAmount": 1,
  "CraftAmountStepSize": 1,
  "CraftAmountMultiplier": 1,
  "Requirements": null,
  "AltRequirements": null,
  "Cost": {
    "SpaceStationMarkup": 0,
    "LowPriceMod": -0.1,
    "HighPriceMod": 0.1,
    "BuyBaseMarkup": 0.2,
    "BuyMarkupMod": 0
  },
  "RecipeCost": 1,
  "SpecificChargeOnly": false,
  "NormalisedValueOnWorld": 0.0000896794954,
  "NormalisedValueOffWorld": 0.0000896794954,
  "TradeCategory": "None",
  "WikiCategory": "Cooking",
  "FossilCategory": "None",
  "CorvettePartCategory": "None",
  "CorvetteRewardFrequency": 0,
  "IsCraftable": false,
  "DeploysInto": "",
  "EconomyInfluenceMultiplier": 0.33,
  "PinObjective": "",
  "PinObjectiveTip": "",
  "PinObjectiveMessage": "",
  "PinObjectiveScannableType": "None",
  "PinObjectiveEasyToRefine": false,
  "NeverPinnable": false,
  "CookingIngredient": true,
  "CookingValue": 0.15,
  "FoodBonusStat": "Suit_Stamina_Recovery",
  "FoodBonusStatAmount": 0,
  "GoodForSelling": false,
  "GiveRewardOnSpecialPurchase": "",
  "EggModifierIngredient": true,
  "IsTechbox": false,
  "CanSendToOtherPlayers": true
}